pyecharts/__init__.py
pyecharts/_version.py
pyecharts/exceptions.py
pyecharts/faker.py
pyecharts/globals.py
pyecharts/types.py
pyecharts/charts/__init__.py
pyecharts/charts/base.py
pyecharts/charts/chart.py
pyecharts/charts/mixins.py
pyecharts/charts/basic_charts/__init__.py
pyecharts/charts/basic_charts/amap.py
pyecharts/charts/basic_charts/bar.py
pyecharts/charts/basic_charts/bmap.py
pyecharts/charts/basic_charts/boxplot.py
pyecharts/charts/basic_charts/calendar.py
pyecharts/charts/basic_charts/custom.py
pyecharts/charts/basic_charts/effectscatter.py
pyecharts/charts/basic_charts/funnel.py
pyecharts/charts/basic_charts/gauge.py
pyecharts/charts/basic_charts/geo.py
pyecharts/charts/basic_charts/graph.py
pyecharts/charts/basic_charts/heatmap.py
pyecharts/charts/basic_charts/kline.py
pyecharts/charts/basic_charts/line.py
pyecharts/charts/basic_charts/liquid.py
pyecharts/charts/basic_charts/map.py
pyecharts/charts/basic_charts/parallel.py
pyecharts/charts/basic_charts/pictorialbar.py
pyecharts/charts/basic_charts/pie.py
pyecharts/charts/basic_charts/polar.py
pyecharts/charts/basic_charts/radar.py
pyecharts/charts/basic_charts/sankey.py
pyecharts/charts/basic_charts/scatter.py
pyecharts/charts/basic_charts/sunburst.py
pyecharts/charts/basic_charts/themeriver.py
pyecharts/charts/basic_charts/tree.py
pyecharts/charts/basic_charts/treemap.py
pyecharts/charts/basic_charts/wordcloud.py
pyecharts/charts/composite_charts/__init__.py
pyecharts/charts/composite_charts/grid.py
pyecharts/charts/composite_charts/page.py
pyecharts/charts/composite_charts/tab.py
pyecharts/charts/composite_charts/timeline.py
pyecharts/charts/three_axis_charts/__init__.py
pyecharts/charts/three_axis_charts/bar3D.py
pyecharts/charts/three_axis_charts/graph_gl.py
pyecharts/charts/three_axis_charts/line3D.py
pyecharts/charts/three_axis_charts/lines3D.py
pyecharts/charts/three_axis_charts/map3D.py
pyecharts/charts/three_axis_charts/map_globe.py
pyecharts/charts/three_axis_charts/scatter3D.py
pyecharts-2.0.7.dist-info/LICENSE
pyecharts-2.0.7.dist-info/METADATA
pyecharts-2.0.7.dist-info/WHEEL
pyecharts-2.0.7.dist-info/top_level.txt
pyecharts-2.0.7.dist-info/RECORD
